chemtsv3/__init__.py
chemtsv3/cli/__init__.py
chemtsv3/cli/generation.py
chemtsv3/cli/model_training.py
chemtsv3/data/__init__.py
chemtsv3/data/filtering_substruct_oota_cho.csv
chemtsv3/data/gbgm/p1.p
chemtsv3/data/gbgm/p_ring.p
chemtsv3/data/gbgm/r_s1.p
chemtsv3/data/gbgm/rs_make_ring.p
chemtsv3/data/gbgm/rs_ring.p
chemtsv3/data/j_score/cycle_scores.txt
chemtsv3/data/j_score/logP_values.txt
chemtsv3/data/j_score/SA_scores.txt
chemtsv3/data/pubchem_filter/atoms_dict.txt
chemtsv3/data/pubchem_filter/bonds_dict.txt
chemtsv3/data/pubchem_filter/metadata.py
chemtsv3/filter/__init__.py
chemtsv3/filter/aromatic_ring_filter.py
chemtsv3/filter/atom_count_filter.py
chemtsv3/filter/base.py
chemtsv3/filter/catalog_filter.py
chemtsv3/filter/charge_filter.py
chemtsv3/filter/connectivity_filter.py
chemtsv3/filter/hba_filter.py
chemtsv3/filter/hbd_filter.py
chemtsv3/filter/heavy_atom_count_filter.py
chemtsv3/filter/known_list_filter.py
chemtsv3/filter/lipinski_filter.py
chemtsv3/filter/log_p_filter.py
chemtsv3/filter/pains_filter.py
chemtsv3/filter/pubchem_filter.py
chemtsv3/filter/radical_filter.py
chemtsv3/filter/ring_bond_filter.py
chemtsv3/filter/ring_size_filter.py
chemtsv3/filter/roc_filter.py
chemtsv3/filter/rotatable_bonds_filter.py
chemtsv3/filter/sa_score_filter.py
chemtsv3/filter/substructure_filter.py
chemtsv3/filter/tpsa_filter.py
chemtsv3/filter/validity_filter.py
chemtsv3/filter/weight_filter.py
chemtsv3/generator/__init__.py
chemtsv3/generator/async_parallel_mcts.py
chemtsv3/generator/base.py
chemtsv3/generator/heapq_generator.py
chemtsv3/generator/mcts.py
chemtsv3/generator/random_generator.py
chemtsv3/language/__init__.py
chemtsv3/language/base.py
chemtsv3/language/fasta.py
chemtsv3/language/helm.py
chemtsv3/language/selfies.py
chemtsv3/language/smiles.py
chemtsv3/language/tokenizer.py
chemtsv3/node/__init__.py
chemtsv3/node/base.py
chemtsv3/node/selfies_string_node.py
chemtsv3/node/sentence_node.py
chemtsv3/node/string_node.py
chemtsv3/policy/__init__.py
chemtsv3-1.0.0.dist-info/entry_points.txt
chemtsv3-1.0.0.dist-info/METADATA
chemtsv3-1.0.0.dist-info/WHEEL
chemtsv3-1.0.0.dist-info/RECORD
