Metadata-Version: 2.4
Name: chemtsv3
Version: 1.0.0
Summary: ChemTSv3: 
License: MIT
Author: Satoru Fujii
Author-email: fujii.sat.rk@yokohama-cu.ac.jp
Requires-Python: >=3.11
Classifier: License :: OSI Approved :: MIT License
Classifier: Programming Language :: Python :: 3
Classifier: Programming Language :: Python :: 3.11
Classifier: Programming Language :: Python :: 3.12
Classifier: Programming Language :: Python :: 3.13
Classifier: Programming Language :: Python :: 3.14
Project-URL: Repository, https://github.com/molecule-generator-collection/ChemTSv3
